sphinxcontrib/zopeext/__init__.py
sphinxcontrib/zopeext/__version__.py
sphinxcontrib/zopeext/autointerface.py
sphinxcontrib_zopeext-0.4.4.dist-info/METADATA
sphinxcontrib_zopeext-0.4.4.dist-info/WHEEL
sphinxcontrib_zopeext-0.4.4.dist-info/entry_points.txt
sphinxcontrib_zopeext-0.4.4.dist-info/licenses/LICENSE
sphinxcontrib_zopeext-0.4.4.dist-info/RECORD
