Metadata-Version: 2.1
Name: sphinxcontrib-zopeext
Version: 0.4.4
Summary: Provides sphinxcontrib.zopeext.autointerface for documenting Zope interfaces.
Author-Email: Michael McNeil Forbes <mforbes@alum.mit.edu>
License: BSD-2-Clause
Classifier: Operating System :: OS Independent
Classifier: Programming Language :: Python
Classifier: Programming Language :: Python :: 3
Classifier: Programming Language :: Python :: 3.7
Classifier: Programming Language :: Python :: 3.8
Classifier: Programming Language :: Python :: 3.9
Classifier: Programming Language :: Python :: 3.10
Classifier: Programming Language :: Python :: 3.11
Classifier: Programming Language :: Python :: 3.12
Classifier: Programming Language :: Python :: 3.13
Classifier: Programming Language :: Python :: 3.14
Classifier: License :: OSI Approved :: BSD License
Classifier: Development Status :: 4 - Beta
Classifier: Framework :: Sphinx :: Extension
Classifier: Framework :: Zope
Classifier: Topic :: Documentation
Classifier: Topic :: Documentation :: Sphinx
Project-URL: Homepage, https://github.com/sphinx-contrib/zopeext/
Project-URL: Repository, https://github.com/sphinx-contrib/zopeext/
Project-URL: Documentation, https://zopeext.readthedocs.io/en/latest/
Project-URL: Changelog, https://zopeext.readthedocs.io/en/latest/#changelog
Requires-Python: >=3.7
Requires-Dist: zope.interface>=5.5.2
Requires-Dist: Sphinx>=4.5.0
Provides-Extra: test
Requires-Dist: importlib-metadata>=4.8.3; python_version < "3.8" and extra == "test"
Requires-Dist: typing_extensions<4.8.0; python_version < "3.8" and extra == "test"
Requires-Dist: pip>=22.2.1; extra == "test"
Requires-Dist: pytest-cov>=4.0.0; extra == "test"
Requires-Dist: sphinx-testing>=1.0.1; extra == "test"
Requires-Dist: pytest>=7.2.2; extra == "test"
Provides-Extra: doc
Requires-Dist: sphinx-book-theme>=0.0.39; extra == "doc"
Requires-Dist: sphinx-autobuild>=2021.3.14; extra == "doc"
